{
  "name": "stoneholm:point_of_interest",
  "fallback": "minecraft:empty",
  "elements": [
    {
      "weight": 50,
      "element": {
        "location": "stoneholm:poi/carpet_room",
        "processors": "minecraft:empty",
        "projection": "rigid",
        "element_type": "minecraft:single_pool_element"
      }
    },
    {
      "weight": 200,
      "element": {
        "location": "stoneholm:poi/cell_block_4x",
        "processors": "minecraft:empty",
        "projection": "rigid",
        "element_type": "minecraft:single_pool_element"
      }
    },
    {
      "weight": 5,
      "element": {
        "location": "stoneholm:poi/bell_01",
        "processors": "minecraft:empty",
        "projection": "rigid",
        "element_type": "minecraft:single_pool_element"
      }
    },
    {
      "weight": 80,
      "element": {
        "location": "stoneholm:poi/farm_01",
        "processors": "minecraft:empty",
        "projection": "rigid",
        "element_type": "minecraft:single_pool_element"
      }
    },
    {
      "weight": 80,
      "element": {
        "location": "stoneholm:poi/library_01",
        "processors": "minecraft:empty",
        "projection": "rigid",
        "element_type": "minecraft:single_pool_element"
      }
    }
  ]
}